offstack/__init__.py
offstack/__main__.py
offstack/constants.py
offstack/dashboard_window.py
offstack/dialog_window.py
offstack/logger.py
offstack/login_window.py
offstack/managers.py
offstack/utils.py
offstack_app-0.0.1a0.dist-info/LICENSE
offstack_app-0.0.1a0.dist-info/METADATA
offstack_app-0.0.1a0.dist-info/WHEEL
offstack_app-0.0.1a0.dist-info/entry_points.txt
offstack_app-0.0.1a0.dist-info/top_level.txt
offstack_app-0.0.1a0.dist-info/RECORD
